<?xml version="1.0" encoding="UTF-8"?>
<spirit:component xmlns:xilinx="http://www.xilinx.com" xmlns:spirit="http://www.spiritconsortium.org/XMLSchema/SPIRIT/1685-2009" xmlns:xsi="http://www.w3.org/2001/XMLSchema-instance">
  <spirit:vendor>xilinx.com</spirit:vendor>
  <spirit:library>customized_ip</spirit:library>
  <spirit:name>design_1_fir_dec_wrapper_0_0</spirit:name>
  <spirit:version>1.0</spirit:version>
  <spirit:busInterfaces>
    <spirit:busInterface>
      <spirit:name>m_axis</spirit:name>
      <spirit:busType spirit:vendor="xilinx.com" spirit:library="interface" spirit:name="axis" spirit:version="1.0"/>
      <spirit:abstractionType spirit:vendor="xilinx.com" spirit:library="interface" spirit:name="axis_rtl" spirit:version="1.0"/>
      <spirit:master/>
      <spirit:portMaps>
        <spirit:portMap>
          <spirit:logicalPort>
            <spirit:name>TDATA</spirit:name>
          </spirit:logicalPort>
          <spirit:physicalPort>
            <spirit:name>m_axis_tdata</spirit:name>
          </spirit:physicalPort>
        </spirit:portMap>
        <spirit:portMap>
          <spirit:logicalPort>
            <spirit:name>TVALID</spirit:name>
          </spirit:logicalPort>
          <spirit:physicalPort>
            <spirit:name>m_axis_tvalid</spirit:name>
          </spirit:physicalPort>
        </spirit:portMap>
      </spirit:portMaps>
      <spirit:parameters>
        <spirit:parameter>
          <spirit:name>TDATA_NUM_BYTES</spirit:name>
          <spirit:value spirit:format="long" spirit:resolve="generated" spirit:id="BUSIFPARAM_VALUE.M_AXIS.TDATA_NUM_BYTES">6</spirit:value>
          <spirit:vendorExtensions>
            <xilinx:parameterInfo>
              <xilinx:parameterUsage>none</xilinx:parameterUsage>
            </xilinx:parameterInfo>
          </spirit:vendorExtensions>
        </spirit:parameter>
        <spirit:parameter>
          <spirit:name>TDEST_WIDTH</spirit:name>
          <spirit:value spirit:format="long" spirit:resolve="generated" spirit:id="BUSIFPARAM_VALUE.M_AXIS.TDEST_WIDTH">0</spirit:value>
          <spirit:vendorExtensions>
            <xilinx:parameterInfo>
              <xilinx:parameterUsage>none</xilinx:parameterUsage>
            </xilinx:parameterInfo>
          </spirit:vendorExtensions>
        </spirit:parameter>
        <spirit:parameter>
          <spirit:name>TID_WIDTH</spirit:name>
          <spirit:value spirit:format="long" spirit:resolve="generated" spirit:id="BUSIFPARAM_VALUE.M_AXIS.TID_WIDTH">0</spirit:value>
          <spirit:vendorExtensions>
            <xilinx:parameterInfo>
              <xilinx:parameterUsage>none</xilinx:parameterUsage>
            </xilinx:parameterInfo>
          </spirit:vendorExtensions>
        </spirit:parameter>
        <spirit:parameter>
          <spirit:name>TUSER_WIDTH</spirit:name>
          <spirit:value spirit:format="long" spirit:resolve="generated" spirit:id="BUSIFPARAM_VALUE.M_AXIS.TUSER_WIDTH">0</spirit:value>
          <spirit:vendorExtensions>
            <xilinx:parameterInfo>
              <xilinx:parameterUsage>none</xilinx:parameterUsage>
            </xilinx:parameterInfo>
          </spirit:vendorExtensions>
        </spirit:parameter>
        <spirit:parameter>
          <spirit:name>HAS_TREADY</spirit:name>
          <spirit:value spirit:format="long" spirit:resolve="generated" spirit:id="BUSIFPARAM_VALUE.M_AXIS.HAS_TREADY">0</spirit:value>
          <spirit:vendorExtensions>
            <xilinx:parameterInfo>
              <xilinx:parameterUsage>none</xilinx:parameterUsage>
            </xilinx:parameterInfo>
          </spirit:vendorExtensions>
        </spirit:parameter>
        <spirit:parameter>
          <spirit:name>HAS_TSTRB</spirit:name>
          <spirit:value spirit:format="long" spirit:resolve="generated" spirit:id="BUSIFPARAM_VALUE.M_AXIS.HAS_TSTRB">0</spirit:value>
          <spirit:vendorExtensions>
            <xilinx:parameterInfo>
              <xilinx:parameterUsage>none</xilinx:parameterUsage>
            </xilinx:parameterInfo>
          </spirit:vendorExtensions>
        </spirit:parameter>
        <spirit:parameter>
          <spirit:name>HAS_TKEEP</spirit:name>
          <spirit:value spirit:format="long" spirit:resolve="generated" spirit:id="BUSIFPARAM_VALUE.M_AXIS.HAS_TKEEP">0</spirit:value>
          <spirit:vendorExtensions>
            <xilinx:parameterInfo>
              <xilinx:parameterUsage>none</xilinx:parameterUsage>
            </xilinx:parameterInfo>
          </spirit:vendorExtensions>
        </spirit:parameter>
        <spirit:parameter>
          <spirit:name>HAS_TLAST</spirit:name>
          <spirit:value spirit:format="long" spirit:resolve="generated" spirit:id="BUSIFPARAM_VALUE.M_AXIS.HAS_TLAST">0</spirit:value>
          <spirit:vendorExtensions>
            <xilinx:parameterInfo>
              <xilinx:parameterUsage>none</xilinx:parameterUsage>
            </xilinx:parameterInfo>
          </spirit:vendorExtensions>
        </spirit:parameter>
        <spirit:parameter>
          <spirit:name>FREQ_HZ</spirit:name>
          <spirit:value spirit:format="long" spirit:resolve="generated" spirit:id="BUSIFPARAM_VALUE.M_AXIS.FREQ_HZ">100000000</spirit:value>
          <spirit:vendorExtensions>
            <xilinx:parameterInfo>
              <xilinx:parameterUsage>none</xilinx:parameterUsage>
            </xilinx:parameterInfo>
          </spirit:vendorExtensions>
        </spirit:parameter>
        <spirit:parameter>
          <spirit:name>PHASE</spirit:name>
          <spirit:value spirit:format="float" spirit:resolve="generated" spirit:id="BUSIFPARAM_VALUE.M_AXIS.PHASE">0.0</spirit:value>
          <spirit:vendorExtensions>
            <xilinx:parameterInfo>
              <xilinx:parameterUsage>none</xilinx:parameterUsage>
            </xilinx:parameterInfo>
          </spirit:vendorExtensions>
        </spirit:parameter>
        <spirit:parameter>
          <spirit:name>CLK_DOMAIN</spirit:name>
          <spirit:value spirit:resolve="generated" spirit:id="BUSIFPARAM_VALUE.M_AXIS.CLK_DOMAIN">design_1_clk_wiz_0_0_clk_out1</spirit:value>
          <spirit:vendorExtensions>
            <xilinx:parameterInfo>
              <xilinx:parameterUsage>none</xilinx:parameterUsage>
            </xilinx:parameterInfo>
          </spirit:vendorExtensions>
        </spirit:parameter>
        <spirit:parameter>
          <spirit:name>LAYERED_METADATA</spirit:name>
          <spirit:value spirit:resolve="generated" spirit:id="BUSIFPARAM_VALUE.M_AXIS.LAYERED_METADATA">undef</spirit:value>
          <spirit:vendorExtensions>
            <xilinx:parameterInfo>
              <xilinx:parameterUsage>none</xilinx:parameterUsage>
            </xilinx:parameterInfo>
          </spirit:vendorExtensions>
        </spirit:parameter>
        <spirit:parameter>
          <spirit:name>INSERT_VIP</spirit:name>
          <spirit:value spirit:format="long" spirit:resolve="user" spirit:id="BUSIFPARAM_VALUE.M_AXIS.INSERT_VIP">0</spirit:value>
          <spirit:vendorExtensions>
            <xilinx:parameterInfo>
              <xilinx:parameterUsage>simulation.rtl</xilinx:parameterUsage>
            </xilinx:parameterInfo>
          </spirit:vendorExtensions>
        </spirit:parameter>
      </spirit:parameters>
    </spirit:busInterface>
    <spirit:busInterface>
      <spirit:name>s_axis</spirit:name>
      <spirit:busType spirit:vendor="xilinx.com" spirit:library="interface" spirit:name="axis" spirit:version="1.0"/>
      <spirit:abstractionType spirit:vendor="xilinx.com" spirit:library="interface" spirit:name="axis_rtl" spirit:version="1.0"/>
      <spirit:slave/>
      <spirit:portMaps>
        <spirit:portMap>
          <spirit:logicalPort>
            <spirit:name>TDATA</spirit:name>
          </spirit:logicalPort>
          <spirit:physicalPort>
            <spirit:name>s_axis_tdata</spirit:name>
          </spirit:physicalPort>
        </spirit:portMap>
        <spirit:portMap>
          <spirit:logicalPort>
            <spirit:name>TVALID</spirit:name>
          </spirit:logicalPort>
          <spirit:physicalPort>
            <spirit:name>s_axis_tvalid</spirit:name>
          </spirit:physicalPort>
        </spirit:portMap>
      </spirit:portMaps>
      <spirit:parameters>
        <spirit:parameter>
          <spirit:name>TDATA_NUM_BYTES</spirit:name>
          <spirit:value spirit:format="long" spirit:resolve="generated" spirit:id="BUSIFPARAM_VALUE.S_AXIS.TDATA_NUM_BYTES">1</spirit:value>
          <spirit:vendorExtensions>
            <xilinx:parameterInfo>
              <xilinx:parameterUsage>none</xilinx:parameterUsage>
            </xilinx:parameterInfo>
          </spirit:vendorExtensions>
        </spirit:parameter>
        <spirit:parameter>
          <spirit:name>TDEST_WIDTH</spirit:name>
          <spirit:value spirit:format="long" spirit:resolve="generated" spirit:id="BUSIFPARAM_VALUE.S_AXIS.TDEST_WIDTH">0</spirit:value>
          <spirit:vendorExtensions>
            <xilinx:parameterInfo>
              <xilinx:parameterUsage>none</xilinx:parameterUsage>
            </xilinx:parameterInfo>
          </spirit:vendorExtensions>
        </spirit:parameter>
        <spirit:parameter>
          <spirit:name>TID_WIDTH</spirit:name>
          <spirit:value spirit:format="long" spirit:resolve="generated" spirit:id="BUSIFPARAM_VALUE.S_AXIS.TID_WIDTH">0</spirit:value>
          <spirit:vendorExtensions>
            <xilinx:parameterInfo>
              <xilinx:parameterUsage>none</xilinx:parameterUsage>
            </xilinx:parameterInfo>
          </spirit:vendorExtensions>
        </spirit:parameter>
        <spirit:parameter>
          <spirit:name>TUSER_WIDTH</spirit:name>
          <spirit:value spirit:format="long" spirit:resolve="generated" spirit:id="BUSIFPARAM_VALUE.S_AXIS.TUSER_WIDTH">0</spirit:value>
          <spirit:vendorExtensions>
            <xilinx:parameterInfo>
              <xilinx:parameterUsage>none</xilinx:parameterUsage>
            </xilinx:parameterInfo>
          </spirit:vendorExtensions>
        </spirit:parameter>
        <spirit:parameter>
          <spirit:name>HAS_TREADY</spirit:name>
          <spirit:value spirit:format="long" spirit:resolve="generated" spirit:id="BUSIFPARAM_VALUE.S_AXIS.HAS_TREADY">0</spirit:value>
          <spirit:vendorExtensions>
            <xilinx:parameterInfo>
              <xilinx:parameterUsage>none</xilinx:parameterUsage>
            </xilinx:parameterInfo>
          </spirit:vendorExtensions>
        </spirit:parameter>
        <spirit:parameter>
          <spirit:name>HAS_TSTRB</spirit:name>
          <spirit:value spirit:format="long" spirit:resolve="generated" spirit:id="BUSIFPARAM_VALUE.S_AXIS.HAS_TSTRB">0</spirit:value>
          <spirit:vendorExtensions>
            <xilinx:parameterInfo>
              <xilinx:parameterUsage>none</xilinx:parameterUsage>
            </xilinx:parameterInfo>
          </spirit:vendorExtensions>
        </spirit:parameter>
        <spirit:parameter>
          <spirit:name>HAS_TKEEP</spirit:name>
          <spirit:value spirit:format="long" spirit:resolve="generated" spirit:id="BUSIFPARAM_VALUE.S_AXIS.HAS_TKEEP">0</spirit:value>
          <spirit:vendorExtensions>
            <xilinx:parameterInfo>
              <xilinx:parameterUsage>none</xilinx:parameterUsage>
            </xilinx:parameterInfo>
          </spirit:vendorExtensions>
        </spirit:parameter>
        <spirit:parameter>
          <spirit:name>HAS_TLAST</spirit:name>
          <spirit:value spirit:format="long" spirit:resolve="generated" spirit:id="BUSIFPARAM_VALUE.S_AXIS.HAS_TLAST">0</spirit:value>
          <spirit:vendorExtensions>
            <xilinx:parameterInfo>
              <xilinx:parameterUsage>none</xilinx:parameterUsage>
            </xilinx:parameterInfo>
          </spirit:vendorExtensions>
        </spirit:parameter>
        <spirit:parameter>
          <spirit:name>FREQ_HZ</spirit:name>
          <spirit:value spirit:format="long" spirit:resolve="generated" spirit:id="BUSIFPARAM_VALUE.S_AXIS.FREQ_HZ">100000000</spirit:value>
          <spirit:vendorExtensions>
            <xilinx:parameterInfo>
              <xilinx:parameterUsage>none</xilinx:parameterUsage>
            </xilinx:parameterInfo>
          </spirit:vendorExtensions>
        </spirit:parameter>
        <spirit:parameter>
          <spirit:name>PHASE</spirit:name>
          <spirit:value spirit:format="float" spirit:resolve="generated" spirit:id="BUSIFPARAM_VALUE.S_AXIS.PHASE">0.0</spirit:value>
          <spirit:vendorExtensions>
            <xilinx:parameterInfo>
              <xilinx:parameterUsage>none</xilinx:parameterUsage>
            </xilinx:parameterInfo>
          </spirit:vendorExtensions>
        </spirit:parameter>
        <spirit:parameter>
          <spirit:name>CLK_DOMAIN</spirit:name>
          <spirit:value spirit:resolve="generated" spirit:id="BUSIFPARAM_VALUE.S_AXIS.CLK_DOMAIN">design_1_clk_wiz_0_0_clk_out1</spirit:value>
          <spirit:vendorExtensions>
            <xilinx:parameterInfo>
              <xilinx:parameterUsage>none</xilinx:parameterUsage>
            </xilinx:parameterInfo>
          </spirit:vendorExtensions>
        </spirit:parameter>
        <spirit:parameter>
          <spirit:name>LAYERED_METADATA</spirit:name>
          <spirit:value spirit:resolve="generated" spirit:id="BUSIFPARAM_VALUE.S_AXIS.LAYERED_METADATA">xilinx.com:interface:datatypes:1.0 {TDATA {datatype {name {attribs {resolve_type immediate dependency {} format string minimum {} maximum {}} value {}} bitwidth {attribs {resolve_type automatic dependency {} format long minimum {} maximum {}} value 8} bitoffset {attribs {resolve_type immediate dependency {} format long minimum {} maximum {}} value 0} array_type {name {attribs {resolve_type immediate dependency {} format string minimum {} maximum {}} value chan} size {attribs {resolve_type genera
ted dependency chan_size format long minimum {} maximum {}} value 1} stride {attribs {resolve_type generated dependency chan_stride format long minimum {} maximum {}} value 8} datatype {name {attribs {resolve_type immediate dependency {} format string minimum {} maximum {}} value {}} bitwidth {attribs {resolve_type automatic dependency {} format long minimum {} maximum {}} value 8} bitoffset {attribs {resolve_type immediate dependency {} format long minimum {} maximum {}} value 0} struct {field_
cosine {name {attribs {resolve_type immediate dependency {} format string minimum {} maximum {}} value cosine} enabled {attribs {resolve_type generated dependency cosine_enabled format bool minimum {} maximum {}} value true} datatype {name {attribs {resolve_type immediate dependency {} format string minimum {} maximum {}} value {}} bitwidth {attribs {resolve_type generated dependency cosine_width format long minimum {} maximum {}} value 8} bitoffset {attribs {resolve_type immediate dependency {}
 format long minimum {} maximum {}} value 0} real {fixed {fractwidth {attribs {resolve_type generated dependency cosine_fractwidth format long minimum {} maximum {}} value 7} signed {attribs {resolve_type immediate dependency {} format bool minimum {} maximum {}} value true}}}}} field_sine {name {attribs {resolve_type immediate dependency {} format string minimum {} maximum {}} value sine} enabled {attribs {resolve_type generated dependency sine_enabled format bool minimum {} maximum {}} value f
alse} datatype {name {attribs {resolve_type immediate dependency {} format string minimum {} maximum {}} value {}} bitwidth {attribs {resolve_type generated dependency sine_width format long minimum {} maximum {}} value 0} bitoffset {attribs {resolve_type generated dependency sine_offset format long minimum {} maximum {}} value 8} real {fixed {fractwidth {attribs {resolve_type generated dependency sine_fractwidth format long minimum {} maximum {}} value 7} signed {attribs {resolve_type immediate
 dependency {} format bool minimum {} maximum {}} value true}}}}}}}}}} TDATA_WIDTH 8 TUSER {datatype {name {attribs {resolve_type immediate dependency {} format string minimum {} maximum {}} value {}} bitwidth {attribs {resolve_type automatic dependency {} format long minimum {} maximum {}} value 0} bitoffset {attribs {resolve_type immediate dependency {} format long minimum {} maximum {}} value 0} struct {field_chanid {name {attribs {resolve_type immediate dependency {} format string minimum {}
 maximum {}} value chanid} enabled {attribs {resolve_type generated dependency chanid_enabled format bool minimum {} maximum {}} value false} datatype {name {attribs {resolve_type immediate dependency {} format string minimum {} maximum {}} value {}} bitwidth {attribs {resolve_type generated dependency chanid_width format long minimum {} maximum {}} value 0} bitoffset {attribs {resolve_type immediate dependency {} format long minimum {} maximum {}} value 0} integer {signed {attribs {resolve_type
 immediate dependency {} format bool minimum {} maximum {}} value false}}}} field_user {name {attribs {resolve_type immediate dependency {} format string minimum {} maximum {}} value user} enabled {attribs {resolve_type generated dependency user_enabled format bool minimum {} maximum {}} value false} datatype {name {attribs {resolve_type immediate dependency {} format string minimum {} maximum {}} value {}} bitwidth {attribs {resolve_type generated dependency user_width format long minimum {} ma
ximum {}} value 0} bitoffset {attribs {resolve_type generated dependency user_offset format long minimum {} maximum {}} value 0}}}}}} TUSER_WIDTH 0}</spirit:value>
          <spirit:vendorExtensions>
            <xilinx:parameterInfo>
              <xilinx:parameterUsage>none</xilinx:parameterUsage>
            </xilinx:parameterInfo>
          </spirit:vendorExtensions>
        </spirit:parameter>
        <spirit:parameter>
          <spirit:name>INSERT_VIP</spirit:name>
          <spirit:value spirit:format="long" spirit:resolve="user" spirit:id="BUSIFPARAM_VALUE.S_AXIS.INSERT_VIP">0</spirit:value>
          <spirit:vendorExtensions>
            <xilinx:parameterInfo>
              <xilinx:parameterUsage>simulation.rtl</xilinx:parameterUsage>
            </xilinx:parameterInfo>
          </spirit:vendorExtensions>
        </spirit:parameter>
      </spirit:parameters>
    </spirit:busInterface>
    <spirit:busInterface>
      <spirit:name>s_axis_ref</spirit:name>
      <spirit:busType spirit:vendor="xilinx.com" spirit:library="interface" spirit:name="axis" spirit:version="1.0"/>
      <spirit:abstractionType spirit:vendor="xilinx.com" spirit:library="interface" spirit:name="axis_rtl" spirit:version="1.0"/>
      <spirit:slave/>
      <spirit:portMaps>
        <spirit:portMap>
          <spirit:logicalPort>
            <spirit:name>TDATA</spirit:name>
          </spirit:logicalPort>
          <spirit:physicalPort>
            <spirit:name>s_axis_ref_tdata</spirit:name>
          </spirit:physicalPort>
        </spirit:portMap>
        <spirit:portMap>
          <spirit:logicalPort>
            <spirit:name>TVALID</spirit:name>
          </spirit:logicalPort>
          <spirit:physicalPort>
            <spirit:name>s_axis_ref_tvalid</spirit:name>
          </spirit:physicalPort>
        </spirit:portMap>
      </spirit:portMaps>
      <spirit:parameters>
        <spirit:parameter>
          <spirit:name>TDATA_NUM_BYTES</spirit:name>
          <spirit:value spirit:format="long" spirit:resolve="generated" spirit:id="BUSIFPARAM_VALUE.S_AXIS_REF.TDATA_NUM_BYTES">2</spirit:value>
          <spirit:vendorExtensions>
            <xilinx:parameterInfo>
              <xilinx:parameterUsage>none</xilinx:parameterUsage>
            </xilinx:parameterInfo>
          </spirit:vendorExtensions>
        </spirit:parameter>
        <spirit:parameter>
          <spirit:name>TDEST_WIDTH</spirit:name>
          <spirit:value spirit:format="long" spirit:resolve="generated" spirit:id="BUSIFPARAM_VALUE.S_AXIS_REF.TDEST_WIDTH">0</spirit:value>
          <spirit:vendorExtensions>
            <xilinx:parameterInfo>
              <xilinx:parameterUsage>none</xilinx:parameterUsage>
            </xilinx:parameterInfo>
          </spirit:vendorExtensions>
        </spirit:parameter>
        <spirit:parameter>
          <spirit:name>TID_WIDTH</spirit:name>
          <spirit:value spirit:format="long" spirit:resolve="generated" spirit:id="BUSIFPARAM_VALUE.S_AXIS_REF.TID_WIDTH">0</spirit:value>
          <spirit:vendorExtensions>
            <xilinx:parameterInfo>
              <xilinx:parameterUsage>none</xilinx:parameterUsage>
            </xilinx:parameterInfo>
          </spirit:vendorExtensions>
        </spirit:parameter>
        <spirit:parameter>
          <spirit:name>TUSER_WIDTH</spirit:name>
          <spirit:value spirit:format="long" spirit:resolve="generated" spirit:id="BUSIFPARAM_VALUE.S_AXIS_REF.TUSER_WIDTH">0</spirit:value>
          <spirit:vendorExtensions>
            <xilinx:parameterInfo>
              <xilinx:parameterUsage>none</xilinx:parameterUsage>
            </xilinx:parameterInfo>
          </spirit:vendorExtensions>
        </spirit:parameter>
        <spirit:parameter>
          <spirit:name>HAS_TREADY</spirit:name>
          <spirit:value spirit:format="long" spirit:resolve="generated" spirit:id="BUSIFPARAM_VALUE.S_AXIS_REF.HAS_TREADY">0</spirit:value>
          <spirit:vendorExtensions>
            <xilinx:parameterInfo>
              <xilinx:parameterUsage>none</xilinx:parameterUsage>
            </xilinx:parameterInfo>
          </spirit:vendorExtensions>
        </spirit:parameter>
        <spirit:parameter>
          <spirit:name>HAS_TSTRB</spirit:name>
          <spirit:value spirit:format="long" spirit:resolve="generated" spirit:id="BUSIFPARAM_VALUE.S_AXIS_REF.HAS_TSTRB">0</spirit:value>
          <spirit:vendorExtensions>
            <xilinx:parameterInfo>
              <xilinx:parameterUsage>none</xilinx:parameterUsage>
            </xilinx:parameterInfo>
          </spirit:vendorExtensions>
        </spirit:parameter>
        <spirit:parameter>
          <spirit:name>HAS_TKEEP</spirit:name>
          <spirit:value spirit:format="long" spirit:resolve="generated" spirit:id="BUSIFPARAM_VALUE.S_AXIS_REF.HAS_TKEEP">0</spirit:value>
          <spirit:vendorExtensions>
            <xilinx:parameterInfo>
              <xilinx:parameterUsage>none</xilinx:parameterUsage>
            </xilinx:parameterInfo>
          </spirit:vendorExtensions>
        </spirit:parameter>
        <spirit:parameter>
          <spirit:name>HAS_TLAST</spirit:name>
          <spirit:value spirit:format="long" spirit:resolve="generated" spirit:id="BUSIFPARAM_VALUE.S_AXIS_REF.HAS_TLAST">0</spirit:value>
          <spirit:vendorExtensions>
            <xilinx:parameterInfo>
              <xilinx:parameterUsage>none</xilinx:parameterUsage>
            </xilinx:parameterInfo>
          </spirit:vendorExtensions>
        </spirit:parameter>
        <spirit:parameter>
          <spirit:name>FREQ_HZ</spirit:name>
          <spirit:value spirit:format="long" spirit:resolve="generated" spirit:id="BUSIFPARAM_VALUE.S_AXIS_REF.FREQ_HZ">100000000</spirit:value>
          <spirit:vendorExtensions>
            <xilinx:parameterInfo>
              <xilinx:parameterUsage>none</xilinx:parameterUsage>
            </xilinx:parameterInfo>
          </spirit:vendorExtensions>
        </spirit:parameter>
        <spirit:parameter>
          <spirit:name>PHASE</spirit:name>
          <spirit:value spirit:format="float" spirit:resolve="generated" spirit:id="BUSIFPARAM_VALUE.S_AXIS_REF.PHASE">0.0</spirit:value>
          <spirit:vendorExtensions>
            <xilinx:parameterInfo>
              <xilinx:parameterUsage>none</xilinx:parameterUsage>
            </xilinx:parameterInfo>
          </spirit:vendorExtensions>
        </spirit:parameter>
        <spirit:parameter>
          <spirit:name>CLK_DOMAIN</spirit:name>
          <spirit:value spirit:resolve="generated" spirit:id="BUSIFPARAM_VALUE.S_AXIS_REF.CLK_DOMAIN">design_1_clk_wiz_0_0_clk_out1</spirit:value>
          <spirit:vendorExtensions>
            <xilinx:parameterInfo>
              <xilinx:parameterUsage>none</xilinx:parameterUsage>
            </xilinx:parameterInfo>
          </spirit:vendorExtensions>
        </spirit:parameter>
        <spirit:parameter>
          <spirit:name>LAYERED_METADATA</spirit:name>
          <spirit:value spirit:resolve="generated" spirit:id="BUSIFPARAM_VALUE.S_AXIS_REF.LAYERED_METADATA">undef</spirit:value>
          <spirit:vendorExtensions>
            <xilinx:parameterInfo>
              <xilinx:parameterUsage>none</xilinx:parameterUsage>
            </xilinx:parameterInfo>
          </spirit:vendorExtensions>
        </spirit:parameter>
        <spirit:parameter>
          <spirit:name>INSERT_VIP</spirit:name>
          <spirit:value spirit:format="long" spirit:resolve="user" spirit:id="BUSIFPARAM_VALUE.S_AXIS_REF.INSERT_VIP">0</spirit:value>
          <spirit:vendorExtensions>
            <xilinx:parameterInfo>
              <xilinx:parameterUsage>simulation.rtl</xilinx:parameterUsage>
            </xilinx:parameterInfo>
          </spirit:vendorExtensions>
        </spirit:parameter>
      </spirit:parameters>
    </spirit:busInterface>
    <spirit:busInterface>
      <spirit:name>rstn</spirit:name>
      <spirit:busType spirit:vendor="xilinx.com" spirit:library="signal" spirit:name="reset" spirit:version="1.0"/>
      <spirit:abstractionType spirit:vendor="xilinx.com" spirit:library="signal" spirit:name="reset_rtl" spirit:version="1.0"/>
      <spirit:slave/>
      <spirit:portMaps>
        <spirit:portMap>
          <spirit:logicalPort>
            <spirit:name>RST</spirit:name>
          </spirit:logicalPort>
          <spirit:physicalPort>
            <spirit:name>rstn</spirit:name>
          </spirit:physicalPort>
        </spirit:portMap>
      </spirit:portMaps>
      <spirit:parameters>
        <spirit:parameter>
          <spirit:name>POLARITY</spirit:name>
          <spirit:value spirit:id="BUSIFPARAM_VALUE.RSTN.POLARITY" spirit:choiceRef="choice_list_9d8b0d81">ACTIVE_LOW</spirit:value>
        </spirit:parameter>
        <spirit:parameter>
          <spirit:name>INSERT_VIP</spirit:name>
          <spirit:value spirit:format="long" spirit:resolve="user" spirit:id="BUSIFPARAM_VALUE.RSTN.INSERT_VIP">0</spirit:value>
          <spirit:vendorExtensions>
            <xilinx:parameterInfo>
              <xilinx:parameterUsage>simulation.rtl</xilinx:parameterUsage>
            </xilinx:parameterInfo>
          </spirit:vendorExtensions>
        </spirit:parameter>
      </spirit:parameters>
    </spirit:busInterface>
    <spirit:busInterface>
      <spirit:name>clk</spirit:name>
      <spirit:busType spirit:vendor="xilinx.com" spirit:library="signal" spirit:name="clock" spirit:version="1.0"/>
      <spirit:abstractionType spirit:vendor="xilinx.com" spirit:library="signal" spirit:name="clock_rtl" spirit:version="1.0"/>
      <spirit:slave/>
      <spirit:portMaps>
        <spirit:portMap>
          <spirit:logicalPort>
            <spirit:name>CLK</spirit:name>
          </spirit:logicalPort>
          <spirit:physicalPort>
            <spirit:name>clk</spirit:name>
          </spirit:physicalPort>
        </spirit:portMap>
      </spirit:portMaps>
      <spirit:parameters>
        <spirit:parameter>
          <spirit:name>ASSOCIATED_BUSIF</spirit:name>
          <spirit:value spirit:id="BUSIFPARAM_VALUE.CLK.ASSOCIATED_BUSIF">m_axis:s_axis:s_axis_ref</spirit:value>
        </spirit:parameter>
        <spirit:parameter>
          <spirit:name>ASSOCIATED_RESET</spirit:name>
          <spirit:value spirit:id="BUSIFPARAM_VALUE.CLK.ASSOCIATED_RESET">rstn</spirit:value>
        </spirit:parameter>
        <spirit:parameter>
          <spirit:name>FREQ_HZ</spirit:name>
          <spirit:value spirit:format="long" spirit:resolve="generated" spirit:id="BUSIFPARAM_VALUE.CLK.FREQ_HZ">100000000</spirit:value>
          <spirit:vendorExtensions>
            <xilinx:parameterInfo>
              <xilinx:parameterUsage>none</xilinx:parameterUsage>
            </xilinx:parameterInfo>
          </spirit:vendorExtensions>
        </spirit:parameter>
        <spirit:parameter>
          <spirit:name>PHASE</spirit:name>
          <spirit:value spirit:format="float" spirit:resolve="generated" spirit:id="BUSIFPARAM_VALUE.CLK.PHASE">0.0</spirit:value>
          <spirit:vendorExtensions>
            <xilinx:parameterInfo>
              <xilinx:parameterUsage>none</xilinx:parameterUsage>
            </xilinx:parameterInfo>
          </spirit:vendorExtensions>
        </spirit:parameter>
        <spirit:parameter>
          <spirit:name>CLK_DOMAIN</spirit:name>
          <spirit:value spirit:resolve="generated" spirit:id="BUSIFPARAM_VALUE.CLK.CLK_DOMAIN">design_1_clk_wiz_0_0_clk_out1</spirit:value>
          <spirit:vendorExtensions>
            <xilinx:parameterInfo>
              <xilinx:parameterUsage>none</xilinx:parameterUsage>
            </xilinx:parameterInfo>
          </spirit:vendorExtensions>
        </spirit:parameter>
        <spirit:parameter>
          <spirit:name>INSERT_VIP</spirit:name>
          <spirit:value spirit:format="long" spirit:resolve="user" spirit:id="BUSIFPARAM_VALUE.CLK.INSERT_VIP">0</spirit:value>
          <spirit:vendorExtensions>
            <xilinx:parameterInfo>
              <xilinx:parameterUsage>simulation.rtl</xilinx:parameterUsage>
            </xilinx:parameterInfo>
          </spirit:vendorExtensions>
        </spirit:parameter>
      </spirit:parameters>
    </spirit:busInterface>
  </spirit:busInterfaces>
  <spirit:model>
    <spirit:views>
      <spirit:view>
        <spirit:name>xilinx_anylanguagesynthesis</spirit:name>
        <spirit:displayName>Synthesis</spirit:displayName>
        <spirit:envIdentifier>:vivado.xilinx.com:synthesis</spirit:envIdentifier>
        <spirit:modelName>fir_dec_wrapper</spirit:modelName>
        <spirit:parameters>
          <spirit:parameter>
            <spirit:name>outputProductCRC</spirit:name>
            <spirit:value>9:07ddb70c</spirit:value>
          </spirit:parameter>
        </spirit:parameters>
      </spirit:view>
      <spirit:view>
        <spirit:name>xilinx_synthesisconstraints</spirit:name>
        <spirit:displayName>Synthesis Constraints</spirit:displayName>
        <spirit:envIdentifier>:vivado.xilinx.com:synthesis.constraints</spirit:envIdentifier>
        <spirit:parameters>
          <spirit:parameter>
            <spirit:name>outputProductCRC</spirit:name>
            <spirit:value>9:07ddb70c</spirit:value>
          </spirit:parameter>
        </spirit:parameters>
      </spirit:view>
      <spirit:view>
        <spirit:name>xilinx_verilogsynthesiswrapper</spirit:name>
        <spirit:displayName>Verilog Synthesis Wrapper</spirit:displayName>
        <spirit:envIdentifier>verilogSource:vivado.xilinx.com:synthesis.wrapper</spirit:envIdentifier>
        <spirit:language>verilog</spirit:language>
        <spirit:modelName>design_1_fir_dec_wrapper_0_0</spirit:modelName>
        <spirit:fileSetRef>
          <spirit:localName>xilinx_verilogsynthesiswrapper_view_fileset</spirit:localName>
        </spirit:fileSetRef>
        <spirit:parameters>
          <spirit:parameter>
            <spirit:name>GENtimestamp</spirit:name>
            <spirit:value>Tue Dec 15 07:02:35 UTC 2020</spirit:value>
          </spirit:parameter>
          <spirit:parameter>
            <spirit:name>outputProductCRC</spirit:name>
            <spirit:value>9:07ddb70c</spirit:value>
          </spirit:parameter>
        </spirit:parameters>
      </spirit:view>
      <spirit:view>
        <spirit:name>xilinx_anylanguagebehavioralsimulation</spirit:name>
        <spirit:displayName>Simulation</spirit:displayName>
        <spirit:envIdentifier>:vivado.xilinx.com:simulation</spirit:envIdentifier>
        <spirit:modelName>fir_dec_wrapper</spirit:modelName>
        <spirit:parameters>
          <spirit:parameter>
            <spirit:name>outputProductCRC</spirit:name>
            <spirit:value>9:c35514f2</spirit:value>
          </spirit:parameter>
        </spirit:parameters>
      </spirit:view>
      <spirit:view>
        <spirit:name>xilinx_verilogsimulationwrapper</spirit:name>
        <spirit:displayName>Verilog Simulation Wrapper</spirit:displayName>
        <spirit:envIdentifier>verilogSource:vivado.xilinx.com:simulation.wrapper</spirit:envIdentifier>
        <spirit:language>verilog</spirit:language>
        <spirit:modelName>design_1_fir_dec_wrapper_0_0</spirit:modelName>
        <spirit:fileSetRef>
          <spirit:localName>xilinx_verilogsimulationwrapper_view_fileset</spirit:localName>
        </spirit:fileSetRef>
        <spirit:parameters>
          <spirit:parameter>
            <spirit:name>GENtimestamp</spirit:name>
            <spirit:value>Tue Dec 15 07:02:35 UTC 2020</spirit:value>
          </spirit:parameter>
          <spirit:parameter>
            <spirit:name>outputProductCRC</spirit:name>
            <spirit:value>9:c35514f2</spirit:value>
          </spirit:parameter>
        </spirit:parameters>
      </spirit:view>
      <spirit:view>
        <spirit:name>xilinx_externalfiles</spirit:name>
        <spirit:displayName>External Files</spirit:displayName>
        <spirit:envIdentifier>:vivado.xilinx.com:external.files</spirit:envIdentifier>
        <spirit:fileSetRef>
          <spirit:localName>xilinx_externalfiles_view_fileset</spirit:localName>
        </spirit:fileSetRef>
        <spirit:parameters>
          <spirit:parameter>
            <spirit:name>GENtimestamp</spirit:name>
            <spirit:value>Tue Dec 15 07:06:27 UTC 2020</spirit:value>
          </spirit:parameter>
          <spirit:parameter>
            <spirit:name>outputProductCRC</spirit:name>
            <spirit:value>9:07ddb70c</spirit:value>
          </spirit:parameter>
        </spirit:parameters>
      </spirit:view>
    </spirit:views>
    <spirit:ports>
      <spirit:port>
        <spirit:name>clk</spirit:name>
        <spirit:wire>
          <spirit:direction>in</spirit:direction>
          <spirit:wireTypeDefs>
            <spirit:wireTypeDef>
              <spirit:typeName>wire</spirit:typeName>
              <spirit:viewNameRef>xilinx_anylanguagesynthesis</spirit:viewNameRef>
              <spirit:viewNameRef>xilinx_anylanguagebehavioralsimulation</spirit:viewNameRef>
            </spirit:wireTypeDef>
          </spirit:wireTypeDefs>
        </spirit:wire>
      </spirit:port>
      <spirit:port>
        <spirit:name>rstn</spirit:name>
        <spirit:wire>
          <spirit:direction>in</spirit:direction>
          <spirit:wireTypeDefs>
            <spirit:wireTypeDef>
              <spirit:typeName>wire</spirit:typeName>
              <spirit:viewNameRef>xilinx_anylanguagesynthesis</spirit:viewNameRef>
              <spirit:viewNameRef>xilinx_anylanguagebehavioralsimulation</spirit:viewNameRef>
            </spirit:wireTypeDef>
          </spirit:wireTypeDefs>
        </spirit:wire>
      </spirit:port>
      <spirit:port>
        <spirit:name>s_axis_tdata</spirit:name>
        <spirit:wire>
          <spirit:direction>in</spirit:direction>
          <spirit:vector>
            <spirit:left spirit:format="long" spirit:resolve="dependent" spirit:dependency="(spirit:decode(id(&apos;MODELPARAM_VALUE.D_W&apos;)) - 1)">7</spirit:left>
            <spirit:right spirit:format="long">0</spirit:right>
          </spirit:vector>
          <spirit:wireTypeDefs>
            <spirit:wireTypeDef>
              <spirit:typeName>wire</spirit:typeName>
              <spirit:viewNameRef>xilinx_anylanguagesynthesis</spirit:viewNameRef>
              <spirit:viewNameRef>xilinx_anylanguagebehavioralsimulation</spirit:viewNameRef>
            </spirit:wireTypeDef>
          </spirit:wireTypeDefs>
          <spirit:driver>
            <spirit:defaultValue spirit:format="long">0</spirit:defaultValue>
          </spirit:driver>
        </spirit:wire>
      </spirit:port>
      <spirit:port>
        <spirit:name>s_axis_tvalid</spirit:name>
        <spirit:wire>
          <spirit:direction>in</spirit:direction>
          <spirit:wireTypeDefs>
            <spirit:wireTypeDef>
              <spirit:typeName>wire</spirit:typeName>
              <spirit:viewNameRef>xilinx_anylanguagesynthesis</spirit:viewNameRef>
              <spirit:viewNameRef>xilinx_anylanguagebehavioralsimulation</spirit:viewNameRef>
            </spirit:wireTypeDef>
          </spirit:wireTypeDefs>
        </spirit:wire>
      </spirit:port>
      <spirit:port>
        <spirit:name>s_axis_ref_tdata</spirit:name>
        <spirit:wire>
          <spirit:direction>in</spirit:direction>
          <spirit:vector>
            <spirit:left spirit:format="long">15</spirit:left>
            <spirit:right spirit:format="long">0</spirit:right>
          </spirit:vector>
          <spirit:wireTypeDefs>
            <spirit:wireTypeDef>
              <spirit:typeName>wire</spirit:typeName>
              <spirit:viewNameRef>xilinx_anylanguagesynthesis</spirit:viewNameRef>
              <spirit:viewNameRef>xilinx_anylanguagebehavioralsimulation</spirit:viewNameRef>
            </spirit:wireTypeDef>
          </spirit:wireTypeDefs>
          <spirit:driver>
            <spirit:defaultValue spirit:format="long">0</spirit:defaultValue>
          </spirit:driver>
        </spirit:wire>
      </spirit:port>
      <spirit:port>
        <spirit:name>s_axis_ref_tvalid</spirit:name>
        <spirit:wire>
          <spirit:direction>in</spirit:direction>
          <spirit:wireTypeDefs>
            <spirit:wireTypeDef>
              <spirit:typeName>wire</spirit:typeName>
              <spirit:viewNameRef>xilinx_anylanguagesynthesis</spirit:viewNameRef>
              <spirit:viewNameRef>xilinx_anylanguagebehavioralsimulation</spirit:viewNameRef>
            </spirit:wireTypeDef>
          </spirit:wireTypeDefs>
        </spirit:wire>
      </spirit:port>
      <spirit:port>
        <spirit:name>m_axis_tdata</spirit:name>
        <spirit:wire>
          <spirit:direction>out</spirit:direction>
          <spirit:vector>
            <spirit:left spirit:format="long" spirit:resolve="dependent" spirit:dependency="((2 * ((0 + spirit:decode(id(&apos;MODELPARAM_VALUE.C_W&apos;))) + spirit:decode(id(&apos;MODELPARAM_VALUE.D_W&apos;)))) - 1)">47</spirit:left>
            <spirit:right spirit:format="long">0</spirit:right>
          </spirit:vector>
          <spirit:wireTypeDefs>
            <spirit:wireTypeDef>
              <spirit:typeName>wire</spirit:typeName>
              <spirit:viewNameRef>xilinx_anylanguagesynthesis</spirit:viewNameRef>
              <spirit:viewNameRef>xilinx_anylanguagebehavioralsimulation</spirit:viewNameRef>
            </spirit:wireTypeDef>
          </spirit:wireTypeDefs>
        </spirit:wire>
      </spirit:port>
      <spirit:port>
        <spirit:name>m_axis_tvalid</spirit:name>
        <spirit:wire>
          <spirit:direction>out</spirit:direction>
          <spirit:wireTypeDefs>
            <spirit:wireTypeDef>
              <spirit:typeName>wire</spirit:typeName>
              <spirit:viewNameRef>xilinx_anylanguagesynthesis</spirit:viewNameRef>
              <spirit:viewNameRef>xilinx_anylanguagebehavioralsimulation</spirit:viewNameRef>
            </spirit:wireTypeDef>
          </spirit:wireTypeDefs>
        </spirit:wire>
      </spirit:port>
    </spirit:ports>
    <spirit:modelParameters>
      <spirit:modelParameter xsi:type="spirit:nameValueTypeType" spirit:dataType="integer">
        <spirit:name>D_W</spirit:name>
        <spirit:displayName>D W</spirit:displayName>
        <spirit:value spirit:format="long" spirit:resolve="generated" spirit:id="MODELPARAM_VALUE.D_W">8</spirit:value>
      </spirit:modelParameter>
      <spirit:modelParameter spirit:dataType="integer">
        <spirit:name>C_W</spirit:name>
        <spirit:displayName>C W</spirit:displayName>
        <spirit:value spirit:format="long" spirit:resolve="generated" spirit:id="MODELPARAM_VALUE.C_W">16</spirit:value>
      </spirit:modelParameter>
      <spirit:modelParameter spirit:dataType="integer">
        <spirit:name>TAPS</spirit:name>
        <spirit:displayName>Taps</spirit:displayName>
        <spirit:value spirit:format="long" spirit:resolve="generated" spirit:id="MODELPARAM_VALUE.TAPS">32</spirit:value>
      </spirit:modelParameter>
      <spirit:modelParameter spirit:dataType="string">
        <spirit:name>MEM_FILE</spirit:name>
        <spirit:displayName>Mem File</spirit:displayName>
        <spirit:value spirit:resolve="generated" spirit:id="MODELPARAM_VALUE.MEM_FILE">[pwd]/$project_name/$project_name.srcs/sources_1/imports/hdl/coef_lp_dec.mem</spirit:value>
      </spirit:modelParameter>
      <spirit:modelParameter spirit:dataType="integer">
        <spirit:name>DECIMATE</spirit:name>
        <spirit:displayName>Decimate</spirit:displayName>
        <spirit:value spirit:format="long" spirit:resolve="generated" spirit:id="MODELPARAM_VALUE.DECIMATE">10</spirit:value>
      </spirit:modelParameter>
    </spirit:modelParameters>
  </spirit:model>
  <spirit:choices>
    <spirit:choice>
      <spirit:name>choice_list_9d8b0d81</spirit:name>
      <spirit:enumeration>ACTIVE_HIGH</spirit:enumeration>
      <spirit:enumeration>ACTIVE_LOW</spirit:enumeration>
    </spirit:choice>
  </spirit:choices>
  <spirit:fileSets>
    <spirit:fileSet>
      <spirit:name>xilinx_verilogsynthesiswrapper_view_fileset</spirit:name>
      <spirit:file>
        <spirit:name>synth/design_1_fir_dec_wrapper_0_0.v</spirit:name>
        <spirit:fileType>verilogSource</spirit:fileType>
        <spirit:logicalName>xil_defaultlib</spirit:logicalName>
      </spirit:file>
    </spirit:fileSet>
    <spirit:fileSet>
      <spirit:name>xilinx_verilogsimulationwrapper_view_fileset</spirit:name>
      <spirit:file>
        <spirit:name>sim/design_1_fir_dec_wrapper_0_0.v</spirit:name>
        <spirit:fileType>verilogSource</spirit:fileType>
        <spirit:logicalName>xil_defaultlib</spirit:logicalName>
      </spirit:file>
    </spirit:fileSet>
    <spirit:fileSet>
      <spirit:name>xilinx_externalfiles_view_fileset</spirit:name>
      <spirit:file>
        <spirit:name>design_1_fir_dec_wrapper_0_0.dcp</spirit:name>
        <spirit:userFileType>dcp</spirit:userFileType>
        <spirit:userFileType>USED_IN_implementation</spirit:userFileType>
        <spirit:userFileType>USED_IN_synthesis</spirit:userFileType>
        <spirit:logicalName>xil_defaultlib</spirit:logicalName>
      </spirit:file>
      <spirit:file>
        <spirit:name>design_1_fir_dec_wrapper_0_0_stub.v</spirit:name>
        <spirit:fileType>verilogSource</spirit:fileType>
        <spirit:userFileType>USED_IN_synth_blackbox_stub</spirit:userFileType>
        <spirit:logicalName>xil_defaultlib</spirit:logicalName>
      </spirit:file>
      <spirit:file>
        <spirit:name>design_1_fir_dec_wrapper_0_0_stub.vhdl</spirit:name>
        <spirit:fileType>vhdlSource</spirit:fileType>
        <spirit:userFileType>USED_IN_synth_blackbox_stub</spirit:userFileType>
        <spirit:logicalName>xil_defaultlib</spirit:logicalName>
      </spirit:file>
      <spirit:file>
        <spirit:name>design_1_fir_dec_wrapper_0_0_sim_netlist.v</spirit:name>
        <spirit:fileType>verilogSource</spirit:fileType>
        <spirit:userFileType>USED_IN_simulation</spirit:userFileType>
        <spirit:userFileType>USED_IN_single_language</spirit:userFileType>
        <spirit:logicalName>xil_defaultlib</spirit:logicalName>
      </spirit:file>
      <spirit:file>
        <spirit:name>design_1_fir_dec_wrapper_0_0_sim_netlist.vhdl</spirit:name>
        <spirit:fileType>vhdlSource</spirit:fileType>
        <spirit:userFileType>USED_IN_simulation</spirit:userFileType>
        <spirit:userFileType>USED_IN_single_language</spirit:userFileType>
        <spirit:logicalName>xil_defaultlib</spirit:logicalName>
      </spirit:file>
    </spirit:fileSet>
  </spirit:fileSets>
  <spirit:description>xilinx.com:module_ref:fir_dec_wrapper:1.0</spirit:description>
  <spirit:parameters>
    <spirit:parameter>
      <spirit:name>D_W</spirit:name>
      <spirit:displayName>D W</spirit:displayName>
      <spirit:value spirit:format="long" spirit:resolve="user" spirit:id="PARAM_VALUE.D_W">8</spirit:value>
    </spirit:parameter>
    <spirit:parameter>
      <spirit:name>C_W</spirit:name>
      <spirit:displayName>C W</spirit:displayName>
      <spirit:value spirit:format="long" spirit:resolve="user" spirit:id="PARAM_VALUE.C_W">16</spirit:value>
    </spirit:parameter>
    <spirit:parameter>
      <spirit:name>TAPS</spirit:name>
      <spirit:displayName>Taps</spirit:displayName>
      <spirit:value spirit:format="long" spirit:resolve="user" spirit:id="PARAM_VALUE.TAPS">32</spirit:value>
    </spirit:parameter>
    <spirit:parameter>
      <spirit:name>MEM_FILE</spirit:name>
      <spirit:displayName>Mem File</spirit:displayName>
      <spirit:value spirit:resolve="user" spirit:id="PARAM_VALUE.MEM_FILE">[pwd]/$project_name/$project_name.srcs/sources_1/imports/hdl/coef_lp_dec.mem</spirit:value>
    </spirit:parameter>
    <spirit:parameter>
      <spirit:name>DECIMATE</spirit:name>
      <spirit:displayName>Decimate</spirit:displayName>
      <spirit:value spirit:format="long" spirit:resolve="user" spirit:id="PARAM_VALUE.DECIMATE">10</spirit:value>
    </spirit:parameter>
    <spirit:parameter>
      <spirit:name>Component_Name</spirit:name>
      <spirit:value spirit:resolve="user" spirit:id="PARAM_VALUE.Component_Name" spirit:order="1">design_1_fir_dec_wrapper_0_0</spirit:value>
    </spirit:parameter>
  </spirit:parameters>
  <spirit:vendorExtensions>
    <xilinx:coreExtensions>
      <xilinx:displayName>fir_dec_wrapper_v1_0</xilinx:displayName>
      <xilinx:definitionSource>module_ref</xilinx:definitionSource>
      <xilinx:coreRevision>1</xilinx:coreRevision>
      <xilinx:configElementInfos>
        <xilinx:configElementInfo xilinx:referenceId="BUSIFPARAM_VALUE.CLK.CLK_DOMAIN" xilinx:valueSource="default_prop" xilinx:valuePermission="bd_and_user"/>
        <xilinx:configElementInfo xilinx:referenceId="BUSIFPARAM_VALUE.CLK.FREQ_HZ" xilinx:valueSource="ip_propagated" xilinx:valuePermission="bd_and_user"/>
        <xilinx:configElementInfo xilinx:referenceId="BUSIFPARAM_VALUE.CLK.PHASE" xilinx:valueSource="ip_propagated" xilinx:valuePermission="bd_and_user"/>
        <xilinx:configElementInfo xilinx:referenceId="BUSIFPARAM_VALUE.M_AXIS.CLK_DOMAIN" xilinx:valueSource="default_prop" xilinx:valuePermission="bd_and_user"/>
        <xilinx:configElementInfo xilinx:referenceId="BUSIFPARAM_VALUE.M_AXIS.FREQ_HZ" xilinx:valueSource="ip_propagated" xilinx:valuePermission="bd_and_user"/>
        <xilinx:configElementInfo xilinx:referenceId="BUSIFPARAM_VALUE.M_AXIS.HAS_TKEEP" xilinx:valueSource="constant" xilinx:valuePermission="bd_and_user"/>
        <xilinx:configElementInfo xilinx:referenceId="BUSIFPARAM_VALUE.M_AXIS.HAS_TLAST" xilinx:valueSource="constant" xilinx:valuePermission="bd_and_user"/>
        <xilinx:configElementInfo xilinx:referenceId="BUSIFPARAM_VALUE.M_AXIS.HAS_TREADY" xilinx:valueSource="constant" xilinx:valuePermission="bd_and_user"/>
        <xilinx:configElementInfo xilinx:referenceId="BUSIFPARAM_VALUE.M_AXIS.HAS_TSTRB" xilinx:valueSource="constant" xilinx:valuePermission="bd_and_user"/>
        <xilinx:configElementInfo xilinx:referenceId="BUSIFPARAM_VALUE.M_AXIS.PHASE" xilinx:valueSource="ip_propagated" xilinx:valuePermission="bd_and_user"/>
        <xilinx:configElementInfo xilinx:referenceId="BUSIFPARAM_VALUE.M_AXIS.TDATA_NUM_BYTES" xilinx:valueSource="auto" xilinx:valuePermission="bd_and_user"/>
        <xilinx:configElementInfo xilinx:referenceId="BUSIFPARAM_VALUE.M_AXIS.TDEST_WIDTH" xilinx:valueSource="constant" xilinx:valuePermission="bd_and_user"/>
        <xilinx:configElementInfo xilinx:referenceId="BUSIFPARAM_VALUE.M_AXIS.TID_WIDTH" xilinx:valueSource="constant" xilinx:valuePermission="bd_and_user"/>
        <xilinx:configElementInfo xilinx:referenceId="BUSIFPARAM_VALUE.M_AXIS.TUSER_WIDTH" xilinx:valueSource="constant" xilinx:valuePermission="bd_and_user"/>
        <xilinx:configElementInfo xilinx:referenceId="BUSIFPARAM_VALUE.S_AXIS.CLK_DOMAIN" xilinx:valueSource="default_prop" xilinx:valuePermission="bd_and_user"/>
        <xilinx:configElementInfo xilinx:referenceId="BUSIFPARAM_VALUE.S_AXIS.FREQ_HZ" xilinx:valueSource="ip_propagated" xilinx:valuePermission="bd_and_user"/>
        <xilinx:configElementInfo xilinx:referenceId="BUSIFPARAM_VALUE.S_AXIS.HAS_TKEEP" xilinx:valueSource="constant" xilinx:valuePermission="bd_and_user"/>
        <xilinx:configElementInfo xilinx:referenceId="BUSIFPARAM_VALUE.S_AXIS.HAS_TLAST" xilinx:valueSource="constant" xilinx:valuePermission="bd_and_user"/>
        <xilinx:configElementInfo xilinx:referenceId="BUSIFPARAM_VALUE.S_AXIS.HAS_TREADY" xilinx:valueSource="constant" xilinx:valuePermission="bd_and_user"/>
        <xilinx:configElementInfo xilinx:referenceId="BUSIFPARAM_VALUE.S_AXIS.HAS_TSTRB" xilinx:valueSource="constant" xilinx:valuePermission="bd_and_user"/>
        <xilinx:configElementInfo xilinx:referenceId="BUSIFPARAM_VALUE.S_AXIS.LAYERED_METADATA" xilinx:valueSource="ip_propagated" xilinx:valuePermission="bd_and_user"/>
        <xilinx:configElementInfo xilinx:referenceId="BUSIFPARAM_VALUE.S_AXIS.PHASE" xilinx:valueSource="ip_propagated" xilinx:valuePermission="bd_and_user"/>
        <xilinx:configElementInfo xilinx:referenceId="BUSIFPARAM_VALUE.S_AXIS.TDATA_NUM_BYTES" xilinx:valueSource="auto" xilinx:valuePermission="bd_and_user"/>
        <xilinx:configElementInfo xilinx:referenceId="BUSIFPARAM_VALUE.S_AXIS.TDEST_WIDTH" xilinx:valueSource="constant" xilinx:valuePermission="bd_and_user"/>
        <xilinx:configElementInfo xilinx:referenceId="BUSIFPARAM_VALUE.S_AXIS.TID_WIDTH" xilinx:valueSource="constant" xilinx:valuePermission="bd_and_user"/>
        <xilinx:configElementInfo xilinx:referenceId="BUSIFPARAM_VALUE.S_AXIS.TUSER_WIDTH" xilinx:valueSource="constant" xilinx:valuePermission="bd_and_user"/>
        <xilinx:configElementInfo xilinx:referenceId="BUSIFPARAM_VALUE.S_AXIS_REF.CLK_DOMAIN" xilinx:valueSource="default_prop" xilinx:valuePermission="bd_and_user"/>
        <xilinx:configElementInfo xilinx:referenceId="BUSIFPARAM_VALUE.S_AXIS_REF.FREQ_HZ" xilinx:valueSource="ip_propagated" xilinx:valuePermission="bd_and_user"/>
        <xilinx:configElementInfo xilinx:referenceId="BUSIFPARAM_VALUE.S_AXIS_REF.HAS_TKEEP" xilinx:valueSource="constant" xilinx:valuePermission="bd_and_user"/>
        <xilinx:configElementInfo xilinx:referenceId="BUSIFPARAM_VALUE.S_AXIS_REF.HAS_TLAST" xilinx:valueSource="constant" xilinx:valuePermission="bd_and_user"/>
        <xilinx:configElementInfo xilinx:referenceId="BUSIFPARAM_VALUE.S_AXIS_REF.HAS_TREADY" xilinx:valueSource="constant" xilinx:valuePermission="bd_and_user"/>
        <xilinx:configElementInfo xilinx:referenceId="BUSIFPARAM_VALUE.S_AXIS_REF.HAS_TSTRB" xilinx:valueSource="constant" xilinx:valuePermission="bd_and_user"/>
        <xilinx:configElementInfo xilinx:referenceId="BUSIFPARAM_VALUE.S_AXIS_REF.PHASE" xilinx:valueSource="ip_propagated" xilinx:valuePermission="bd_and_user"/>
        <xilinx:configElementInfo xilinx:referenceId="BUSIFPARAM_VALUE.S_AXIS_REF.TDATA_NUM_BYTES" xilinx:valueSource="constant" xilinx:valuePermission="bd_and_user"/>
        <xilinx:configElementInfo xilinx:referenceId="BUSIFPARAM_VALUE.S_AXIS_REF.TDEST_WIDTH" xilinx:valueSource="constant" xilinx:valuePermission="bd_and_user"/>
        <xilinx:configElementInfo xilinx:referenceId="BUSIFPARAM_VALUE.S_AXIS_REF.TID_WIDTH" xilinx:valueSource="constant" xilinx:valuePermission="bd_and_user"/>
        <xilinx:configElementInfo xilinx:referenceId="BUSIFPARAM_VALUE.S_AXIS_REF.TUSER_WIDTH" xilinx:valueSource="constant" xilinx:valuePermission="bd_and_user"/>
        <xilinx:configElementInfo xilinx:referenceId="PARAM_VALUE.DECIMATE" xilinx:valueSource="user"/>
        <xilinx:configElementInfo xilinx:referenceId="PARAM_VALUE.MEM_FILE" xilinx:valueSource="user"/>
      </xilinx:configElementInfos>
    </xilinx:coreExtensions>
    <xilinx:packagingInfo>
      <xilinx:xilinxVersion>2019.1.3</xilinx:xilinxVersion>
    </xilinx:packagingInfo>
  </spirit:vendorExtensions>
</spirit:component>
