<?xml version="1.0" encoding="UTF-8"?>
<vivadoHLSLog:LogRoot xmlns:vivadoHLSLog="www.xilinx.com/vivadoHLSLog">
  <errorLogs>
    <logs>
      <synLog/>
      <simLog/>
      <mgLog/>
      <packageLog/>
      <csimLog/>
    </logs>
  </errorLogs>
  <warningLogs>
    <logs>
      <synLog>
        <logs message="WARNING: [HLS 200-631] Ignoring ap_ctrl_none interface for up_conv due to Block__proc14 with non-FIFO I/O" projectName="up_conv" solutionName="solution1" date="2020-12-22T13:01:29.682+0300" type="Warning"/>
        <logs message="WARNING: [RTGEN 206-101] Register 'shift_reg_0' is power-on initialization." projectName="up_conv" solutionName="solution1" date="2020-12-22T13:01:28.762+0300" type="Warning"/>
        <logs message="WARNING: [RTGEN 206-101] Register 'shift_reg_1' is power-on initialization." projectName="up_conv" solutionName="solution1" date="2020-12-22T13:01:28.721+0300" type="Warning"/>
        <logs message="WARNING: [RTGEN 206-101] Register 'shift_reg_2' is power-on initialization." projectName="up_conv" solutionName="solution1" date="2020-12-22T13:01:28.679+0300" type="Warning"/>
        <logs message="WARNING: [RTGEN 206-101] Register 'shift_reg_3' is power-on initialization." projectName="up_conv" solutionName="solution1" date="2020-12-22T13:01:28.637+0300" type="Warning"/>
        <logs message="WARNING: [RTGEN 206-101] Register 'shift_reg_4' is power-on initialization." projectName="up_conv" solutionName="solution1" date="2020-12-22T13:01:28.602+0300" type="Warning"/>
        <logs message="WARNING: [RTGEN 206-101] Register 'shift_reg_5' is power-on initialization." projectName="up_conv" solutionName="solution1" date="2020-12-22T13:01:28.580+0300" type="Warning"/>
        <logs message="WARNING: [RTGEN 206-101] Register 'shift_reg_6' is power-on initialization." projectName="up_conv" solutionName="solution1" date="2020-12-22T13:01:28.558+0300" type="Warning"/>
        <logs message="WARNING: [RTGEN 206-101] Register 'shift_reg_7' is power-on initialization." projectName="up_conv" solutionName="solution1" date="2020-12-22T13:01:28.541+0300" type="Warning"/>
        <logs message="WARNING: [RTGEN 206-101] Register 'shift_reg_8' is power-on initialization." projectName="up_conv" solutionName="solution1" date="2020-12-22T13:01:28.525+0300" type="Warning"/>
        <logs message="WARNING: [RTGEN 206-101] Register 'shift_reg_9' is power-on initialization." projectName="up_conv" solutionName="solution1" date="2020-12-22T13:01:28.497+0300" type="Warning"/>
        <logs message="WARNING: [RTGEN 206-101] Register 'shift_reg_10' is power-on initialization." projectName="up_conv" solutionName="solution1" date="2020-12-22T13:01:28.483+0300" type="Warning"/>
        <logs message="WARNING: [RTGEN 206-101] Register 'shift_reg_11' is power-on initialization." projectName="up_conv" solutionName="solution1" date="2020-12-22T13:01:28.466+0300" type="Warning"/>
        <logs message="WARNING: [RTGEN 206-101] Register 'shift_reg_12' is power-on initialization." projectName="up_conv" solutionName="solution1" date="2020-12-22T13:01:28.445+0300" type="Warning"/>
        <logs message="WARNING: [RTGEN 206-101] Register 'shift_reg_13' is power-on initialization." projectName="up_conv" solutionName="solution1" date="2020-12-22T13:01:28.430+0300" type="Warning"/>
        <logs message="WARNING: [RTGEN 206-101] Register 'shift_reg_14' is power-on initialization." projectName="up_conv" solutionName="solution1" date="2020-12-22T13:01:28.412+0300" type="Warning"/>
        <logs message="WARNING: [RTGEN 206-101] Register 'shift_reg_15' is power-on initialization." projectName="up_conv" solutionName="solution1" date="2020-12-22T13:01:28.393+0300" type="Warning"/>
        <logs message="WARNING: [RTGEN 206-101] Register 'shift_reg_16' is power-on initialization." projectName="up_conv" solutionName="solution1" date="2020-12-22T13:01:28.377+0300" type="Warning"/>
        <logs message="WARNING: [RTGEN 206-101] Register 'shift_reg_17' is power-on initialization." projectName="up_conv" solutionName="solution1" date="2020-12-22T13:01:28.360+0300" type="Warning"/>
        <logs message="WARNING: [RTGEN 206-101] Register 'shift_reg_18' is power-on initialization." projectName="up_conv" solutionName="solution1" date="2020-12-22T13:01:28.285+0300" type="Warning"/>
        <logs message="WARNING: [RTGEN 206-101] Register 'shift_reg_19' is power-on initialization." projectName="up_conv" solutionName="solution1" date="2020-12-22T13:01:28.270+0300" type="Warning"/>
        <logs message="WARNING: [RTGEN 206-101] Register 'shift_reg_20' is power-on initialization." projectName="up_conv" solutionName="solution1" date="2020-12-22T13:01:28.248+0300" type="Warning"/>
        <logs message="WARNING: [RTGEN 206-101] Register 'shift_reg_21' is power-on initialization." projectName="up_conv" solutionName="solution1" date="2020-12-22T13:01:28.223+0300" type="Warning"/>
        <logs message="WARNING: [RTGEN 206-101] Register 'shift_reg_22' is power-on initialization." projectName="up_conv" solutionName="solution1" date="2020-12-22T13:01:28.199+0300" type="Warning"/>
        <logs message="WARNING: [RTGEN 206-101] Register 'shift_reg_23' is power-on initialization." projectName="up_conv" solutionName="solution1" date="2020-12-22T13:01:28.182+0300" type="Warning"/>
        <logs message="WARNING: [RTGEN 206-101] Register 'shift_reg_24' is power-on initialization." projectName="up_conv" solutionName="solution1" date="2020-12-22T13:01:28.155+0300" type="Warning"/>
        <logs message="WARNING: [RTGEN 206-101] Register 'shift_reg_25' is power-on initialization." projectName="up_conv" solutionName="solution1" date="2020-12-22T13:01:28.133+0300" type="Warning"/>
        <logs message="WARNING: [RTGEN 206-101] Register 'shift_reg_26' is power-on initialization." projectName="up_conv" solutionName="solution1" date="2020-12-22T13:01:28.110+0300" type="Warning"/>
        <logs message="WARNING: [RTGEN 206-101] Register 'shift_reg_27' is power-on initialization." projectName="up_conv" solutionName="solution1" date="2020-12-22T13:01:28.088+0300" type="Warning"/>
        <logs message="WARNING: [RTGEN 206-101] Register 'shift_reg_28' is power-on initialization." projectName="up_conv" solutionName="solution1" date="2020-12-22T13:01:28.047+0300" type="Warning"/>
        <logs message="WARNING: [RTGEN 206-101] Register 'shift_reg_29' is power-on initialization." projectName="up_conv" solutionName="solution1" date="2020-12-22T13:01:28.021+0300" type="Warning"/>
        <logs message="WARNING: [RTGEN 206-101] Register 'shift_reg_30' is power-on initialization." projectName="up_conv" solutionName="solution1" date="2020-12-22T13:01:27.996+0300" type="Warning"/>
        <logs message="WARNING: [RTGEN 206-101] Register 'shift_reg_31' is power-on initialization." projectName="up_conv" solutionName="solution1" date="2020-12-22T13:01:27.974+0300" type="Warning"/>
        <logs message="WARNING: [RTGEN 206-101] Register 'shift_reg_32' is power-on initialization." projectName="up_conv" solutionName="solution1" date="2020-12-22T13:01:27.948+0300" type="Warning"/>
        <logs message="WARNING: [RTGEN 206-101] Register 'shift_reg_33' is power-on initialization." projectName="up_conv" solutionName="solution1" date="2020-12-22T13:01:27.928+0300" type="Warning"/>
        <logs message="WARNING: [RTGEN 206-101] Register 'shift_reg_34' is power-on initialization." projectName="up_conv" solutionName="solution1" date="2020-12-22T13:01:27.914+0300" type="Warning"/>
        <logs message="WARNING: [RTGEN 206-101] Register 'shift_reg_35' is power-on initialization." projectName="up_conv" solutionName="solution1" date="2020-12-22T13:01:27.898+0300" type="Warning"/>
        <logs message="WARNING: [RTGEN 206-101] Register 'shift_reg_36' is power-on initialization." projectName="up_conv" solutionName="solution1" date="2020-12-22T13:01:27.879+0300" type="Warning"/>
        <logs message="WARNING: [RTGEN 206-101] Register 'shift_reg_37' is power-on initialization." projectName="up_conv" solutionName="solution1" date="2020-12-22T13:01:27.863+0300" type="Warning"/>
        <logs message="WARNING: [RTGEN 206-101] Register 'shift_reg_38' is power-on initialization." projectName="up_conv" solutionName="solution1" date="2020-12-22T13:01:27.847+0300" type="Warning"/>
        <logs message="WARNING: [RTGEN 206-101] Register 'shift_reg_39' is power-on initialization." projectName="up_conv" solutionName="solution1" date="2020-12-22T13:01:27.826+0300" type="Warning"/>
        <logs message="WARNING: [RTGEN 206-101] Register 'shift_reg_40' is power-on initialization." projectName="up_conv" solutionName="solution1" date="2020-12-22T13:01:27.802+0300" type="Warning"/>
        <logs message="WARNING: [RTGEN 206-101] Register 'shift_reg_41' is power-on initialization." projectName="up_conv" solutionName="solution1" date="2020-12-22T13:01:27.786+0300" type="Warning"/>
        <logs message="WARNING: [RTGEN 206-101] Register 'shift_reg_42' is power-on initialization." projectName="up_conv" solutionName="solution1" date="2020-12-22T13:01:27.762+0300" type="Warning"/>
        <logs message="WARNING: [RTGEN 206-101] Register 'shift_reg_43' is power-on initialization." projectName="up_conv" solutionName="solution1" date="2020-12-22T13:01:27.743+0300" type="Warning"/>
        <logs message="WARNING: [RTGEN 206-101] Register 'shift_reg_44' is power-on initialization." projectName="up_conv" solutionName="solution1" date="2020-12-22T13:01:27.674+0300" type="Warning"/>
        <logs message="WARNING: [RTGEN 206-101] Register 'shift_reg_45' is power-on initialization." projectName="up_conv" solutionName="solution1" date="2020-12-22T13:01:27.654+0300" type="Warning"/>
        <logs message="WARNING: [RTGEN 206-101] Register 'shift_reg_46' is power-on initialization." projectName="up_conv" solutionName="solution1" date="2020-12-22T13:01:27.636+0300" type="Warning"/>
        <logs message="WARNING: [RTGEN 206-101] Register 'shift_reg_47' is power-on initialization." projectName="up_conv" solutionName="solution1" date="2020-12-22T13:01:27.620+0300" type="Warning"/>
        <logs message="WARNING: [RTGEN 206-101] Register 'shift_reg_48' is power-on initialization." projectName="up_conv" solutionName="solution1" date="2020-12-22T13:01:27.598+0300" type="Warning"/>
        <logs message="WARNING: [RTGEN 206-101] Register 'shift_reg_49' is power-on initialization." projectName="up_conv" solutionName="solution1" date="2020-12-22T13:01:27.582+0300" type="Warning"/>
        <logs message="WARNING: [RTGEN 206-101] Register 'shift_reg_50' is power-on initialization." projectName="up_conv" solutionName="solution1" date="2020-12-22T13:01:27.563+0300" type="Warning"/>
        <logs message="WARNING: [RTGEN 206-101] Register 'shift_reg_51' is power-on initialization." projectName="up_conv" solutionName="solution1" date="2020-12-22T13:01:27.550+0300" type="Warning"/>
        <logs message="WARNING: [RTGEN 206-101] Register 'shift_reg_52' is power-on initialization." projectName="up_conv" solutionName="solution1" date="2020-12-22T13:01:27.536+0300" type="Warning"/>
        <logs message="WARNING: [RTGEN 206-101] Register 'shift_reg_53' is power-on initialization." projectName="up_conv" solutionName="solution1" date="2020-12-22T13:01:27.515+0300" type="Warning"/>
        <logs message="WARNING: [RTGEN 206-101] Register 'shift_reg_54' is power-on initialization." projectName="up_conv" solutionName="solution1" date="2020-12-22T13:01:27.500+0300" type="Warning"/>
        <logs message="WARNING: [RTGEN 206-101] Register 'shift_reg_55' is power-on initialization." projectName="up_conv" solutionName="solution1" date="2020-12-22T13:01:27.486+0300" type="Warning"/>
        <logs message="WARNING: [RTGEN 206-101] Register 'shift_reg_56' is power-on initialization." projectName="up_conv" solutionName="solution1" date="2020-12-22T13:01:27.465+0300" type="Warning"/>
        <logs message="WARNING: [RTGEN 206-101] Register 'shift_reg_57' is power-on initialization." projectName="up_conv" solutionName="solution1" date="2020-12-22T13:01:27.451+0300" type="Warning"/>
        <logs message="WARNING: [RTGEN 206-101] Register 'shift_reg_58' is power-on initialization." projectName="up_conv" solutionName="solution1" date="2020-12-22T13:01:27.431+0300" type="Warning"/>
        <logs message="WARNING: [RTGEN 206-101] Register 'shift_reg_59' is power-on initialization." projectName="up_conv" solutionName="solution1" date="2020-12-22T13:01:27.401+0300" type="Warning"/>
        <logs message="WARNING: [RTGEN 206-101] Register 'shift_reg_1_0' is power-on initialization." projectName="up_conv" solutionName="solution1" date="2020-12-22T13:01:25.929+0300" type="Warning"/>
        <logs message="WARNING: [RTGEN 206-101] Register 'shift_reg_1_1' is power-on initialization." projectName="up_conv" solutionName="solution1" date="2020-12-22T13:01:25.909+0300" type="Warning"/>
        <logs message="WARNING: [RTGEN 206-101] Register 'shift_reg_1_2' is power-on initialization." projectName="up_conv" solutionName="solution1" date="2020-12-22T13:01:25.890+0300" type="Warning"/>
        <logs message="WARNING: [RTGEN 206-101] Register 'shift_reg_1_3' is power-on initialization." projectName="up_conv" solutionName="solution1" date="2020-12-22T13:01:25.874+0300" type="Warning"/>
        <logs message="WARNING: [RTGEN 206-101] Register 'shift_reg_1_4' is power-on initialization." projectName="up_conv" solutionName="solution1" date="2020-12-22T13:01:25.853+0300" type="Warning"/>
        <logs message="WARNING: [RTGEN 206-101] Register 'shift_reg_1_5' is power-on initialization." projectName="up_conv" solutionName="solution1" date="2020-12-22T13:01:25.832+0300" type="Warning"/>
        <logs message="WARNING: [RTGEN 206-101] Register 'shift_reg_1_6' is power-on initialization." projectName="up_conv" solutionName="solution1" date="2020-12-22T13:01:25.811+0300" type="Warning"/>
        <logs message="WARNING: [RTGEN 206-101] Register 'shift_reg_1_7' is power-on initialization." projectName="up_conv" solutionName="solution1" date="2020-12-22T13:01:25.797+0300" type="Warning"/>
        <logs message="WARNING: [RTGEN 206-101] Register 'shift_reg_1_8' is power-on initialization." projectName="up_conv" solutionName="solution1" date="2020-12-22T13:01:25.781+0300" type="Warning"/>
        <logs message="WARNING: [RTGEN 206-101] Register 'shift_reg_1_9' is power-on initialization." projectName="up_conv" solutionName="solution1" date="2020-12-22T13:01:25.757+0300" type="Warning"/>
        <logs message="WARNING: [RTGEN 206-101] Register 'shift_reg_1_10' is power-on initialization." projectName="up_conv" solutionName="solution1" date="2020-12-22T13:01:25.729+0300" type="Warning"/>
        <logs message="WARNING: [RTGEN 206-101] Register 'shift_reg_1_11' is power-on initialization." projectName="up_conv" solutionName="solution1" date="2020-12-22T13:01:25.704+0300" type="Warning"/>
        <logs message="WARNING: [RTGEN 206-101] Register 'shift_reg_1_12' is power-on initialization." projectName="up_conv" solutionName="solution1" date="2020-12-22T13:01:25.643+0300" type="Warning"/>
        <logs message="WARNING: [RTGEN 206-101] Register 'shift_reg_1_13' is power-on initialization." projectName="up_conv" solutionName="solution1" date="2020-12-22T13:01:25.629+0300" type="Warning"/>
        <logs message="WARNING: [RTGEN 206-101] Register 'shift_reg_1_14' is power-on initialization." projectName="up_conv" solutionName="solution1" date="2020-12-22T13:01:25.613+0300" type="Warning"/>
        <logs message="WARNING: [RTGEN 206-101] Register 'shift_reg_1_15' is power-on initialization." projectName="up_conv" solutionName="solution1" date="2020-12-22T13:01:25.595+0300" type="Warning"/>
        <logs message="WARNING: [RTGEN 206-101] Register 'shift_reg_1_16' is power-on initialization." projectName="up_conv" solutionName="solution1" date="2020-12-22T13:01:25.567+0300" type="Warning"/>
        <logs message="WARNING: [RTGEN 206-101] Register 'shift_reg_1_17' is power-on initialization." projectName="up_conv" solutionName="solution1" date="2020-12-22T13:01:25.554+0300" type="Warning"/>
        <logs message="WARNING: [RTGEN 206-101] Register 'shift_reg_1_18' is power-on initialization." projectName="up_conv" solutionName="solution1" date="2020-12-22T13:01:25.539+0300" type="Warning"/>
        <logs message="WARNING: [RTGEN 206-101] Register 'shift_reg_1_19' is power-on initialization." projectName="up_conv" solutionName="solution1" date="2020-12-22T13:01:25.521+0300" type="Warning"/>
        <logs message="WARNING: [RTGEN 206-101] Register 'shift_reg_1_20' is power-on initialization." projectName="up_conv" solutionName="solution1" date="2020-12-22T13:01:25.506+0300" type="Warning"/>
        <logs message="WARNING: [RTGEN 206-101] Register 'shift_reg_1_21' is power-on initialization." projectName="up_conv" solutionName="solution1" date="2020-12-22T13:01:25.491+0300" type="Warning"/>
        <logs message="WARNING: [RTGEN 206-101] Register 'shift_reg_1_22' is power-on initialization." projectName="up_conv" solutionName="solution1" date="2020-12-22T13:01:25.475+0300" type="Warning"/>
        <logs message="WARNING: [RTGEN 206-101] Register 'shift_reg_1_23' is power-on initialization." projectName="up_conv" solutionName="solution1" date="2020-12-22T13:01:25.458+0300" type="Warning"/>
        <logs message="WARNING: [RTGEN 206-101] Register 'shift_reg_1_24' is power-on initialization." projectName="up_conv" solutionName="solution1" date="2020-12-22T13:01:25.444+0300" type="Warning"/>
        <logs message="WARNING: [RTGEN 206-101] Register 'shift_reg_1_25' is power-on initialization." projectName="up_conv" solutionName="solution1" date="2020-12-22T13:01:25.425+0300" type="Warning"/>
        <logs message="WARNING: [RTGEN 206-101] Register 'shift_reg_1_26' is power-on initialization." projectName="up_conv" solutionName="solution1" date="2020-12-22T13:01:25.414+0300" type="Warning"/>
        <logs message="WARNING: [RTGEN 206-101] Register 'shift_reg_1_27' is power-on initialization." projectName="up_conv" solutionName="solution1" date="2020-12-22T13:01:25.353+0300" type="Warning"/>
        <logs message="WARNING: [RTGEN 206-101] Register 'shift_reg_1_28' is power-on initialization." projectName="up_conv" solutionName="solution1" date="2020-12-22T13:01:25.334+0300" type="Warning"/>
        <logs message="WARNING: [RTGEN 206-101] Register 'shift_reg_1_29' is power-on initialization." projectName="up_conv" solutionName="solution1" date="2020-12-22T13:01:25.321+0300" type="Warning"/>
        <logs message="WARNING: [RTGEN 206-101] Register 'shift_reg_1_30' is power-on initialization." projectName="up_conv" solutionName="solution1" date="2020-12-22T13:01:25.306+0300" type="Warning"/>
        <logs message="WARNING: [RTGEN 206-101] Register 'shift_reg_1_31' is power-on initialization." projectName="up_conv" solutionName="solution1" date="2020-12-22T13:01:25.287+0300" type="Warning"/>
        <logs message="WARNING: [RTGEN 206-101] Register 'shift_reg_1_32' is power-on initialization." projectName="up_conv" solutionName="solution1" date="2020-12-22T13:01:25.262+0300" type="Warning"/>
        <logs message="WARNING: [RTGEN 206-101] Register 'shift_reg_1_33' is power-on initialization." projectName="up_conv" solutionName="solution1" date="2020-12-22T13:01:25.245+0300" type="Warning"/>
        <logs message="WARNING: [RTGEN 206-101] Register 'shift_reg_1_34' is power-on initialization." projectName="up_conv" solutionName="solution1" date="2020-12-22T13:01:25.226+0300" type="Warning"/>
        <logs message="WARNING: [RTGEN 206-101] Register 'shift_reg_1_35' is power-on initialization." projectName="up_conv" solutionName="solution1" date="2020-12-22T13:01:25.202+0300" type="Warning"/>
        <logs message="WARNING: [RTGEN 206-101] Register 'shift_reg_1_36' is power-on initialization." projectName="up_conv" solutionName="solution1" date="2020-12-22T13:01:25.188+0300" type="Warning"/>
        <logs message="WARNING: [RTGEN 206-101] Register 'shift_reg_1_37' is power-on initialization." projectName="up_conv" solutionName="solution1" date="2020-12-22T13:01:25.175+0300" type="Warning"/>
        <logs message="WARNING: [RTGEN 206-101] Register 'shift_reg_1_38' is power-on initialization." projectName="up_conv" solutionName="solution1" date="2020-12-22T13:01:25.159+0300" type="Warning"/>
        <logs message="WARNING: [RTGEN 206-101] Register 'shift_reg_1_39' is power-on initialization." projectName="up_conv" solutionName="solution1" date="2020-12-22T13:01:25.140+0300" type="Warning"/>
        <logs message="WARNING: [RTGEN 206-101] Register 'shift_reg_1_40' is power-on initialization." projectName="up_conv" solutionName="solution1" date="2020-12-22T13:01:25.126+0300" type="Warning"/>
        <logs message="WARNING: [RTGEN 206-101] Register 'shift_reg_1_41' is power-on initialization." projectName="up_conv" solutionName="solution1" date="2020-12-22T13:01:25.108+0300" type="Warning"/>
        <logs message="WARNING: [RTGEN 206-101] Register 'shift_reg_1_42' is power-on initialization." projectName="up_conv" solutionName="solution1" date="2020-12-22T13:01:25.090+0300" type="Warning"/>
        <logs message="WARNING: [RTGEN 206-101] Register 'shift_reg_1_43' is power-on initialization." projectName="up_conv" solutionName="solution1" date="2020-12-22T13:01:25.073+0300" type="Warning"/>
        <logs message="WARNING: [RTGEN 206-101] Register 'shift_reg_1_44' is power-on initialization." projectName="up_conv" solutionName="solution1" date="2020-12-22T13:01:25.051+0300" type="Warning"/>
        <logs message="WARNING: [RTGEN 206-101] Register 'shift_reg_1_45' is power-on initialization." projectName="up_conv" solutionName="solution1" date="2020-12-22T13:01:25.031+0300" type="Warning"/>
        <logs message="WARNING: [RTGEN 206-101] Register 'shift_reg_1_46' is power-on initialization." projectName="up_conv" solutionName="solution1" date="2020-12-22T13:01:25.014+0300" type="Warning"/>
        <logs message="WARNING: [RTGEN 206-101] Register 'shift_reg_1_47' is power-on initialization." projectName="up_conv" solutionName="solution1" date="2020-12-22T13:01:24.996+0300" type="Warning"/>
        <logs message="WARNING: [RTGEN 206-101] Register 'shift_reg_1_48' is power-on initialization." projectName="up_conv" solutionName="solution1" date="2020-12-22T13:01:24.980+0300" type="Warning"/>
        <logs message="WARNING: [RTGEN 206-101] Register 'shift_reg_1_49' is power-on initialization." projectName="up_conv" solutionName="solution1" date="2020-12-22T13:01:24.919+0300" type="Warning"/>
        <logs message="WARNING: [RTGEN 206-101] Register 'shift_reg_1_50' is power-on initialization." projectName="up_conv" solutionName="solution1" date="2020-12-22T13:01:24.900+0300" type="Warning"/>
        <logs message="WARNING: [RTGEN 206-101] Register 'shift_reg_1_51' is power-on initialization." projectName="up_conv" solutionName="solution1" date="2020-12-22T13:01:24.887+0300" type="Warning"/>
        <logs message="WARNING: [RTGEN 206-101] Register 'shift_reg_1_52' is power-on initialization." projectName="up_conv" solutionName="solution1" date="2020-12-22T13:01:24.870+0300" type="Warning"/>
        <logs message="WARNING: [RTGEN 206-101] Register 'shift_reg_1_53' is power-on initialization." projectName="up_conv" solutionName="solution1" date="2020-12-22T13:01:24.848+0300" type="Warning"/>
        <logs message="WARNING: [RTGEN 206-101] Register 'shift_reg_1_54' is power-on initialization." projectName="up_conv" solutionName="solution1" date="2020-12-22T13:01:24.826+0300" type="Warning"/>
        <logs message="WARNING: [RTGEN 206-101] Register 'shift_reg_1_55' is power-on initialization." projectName="up_conv" solutionName="solution1" date="2020-12-22T13:01:24.804+0300" type="Warning"/>
        <logs message="WARNING: [RTGEN 206-101] Register 'shift_reg_1_56' is power-on initialization." projectName="up_conv" solutionName="solution1" date="2020-12-22T13:01:24.788+0300" type="Warning"/>
        <logs message="WARNING: [RTGEN 206-101] Register 'shift_reg_1_57' is power-on initialization." projectName="up_conv" solutionName="solution1" date="2020-12-22T13:01:24.752+0300" type="Warning"/>
        <logs message="WARNING: [RTGEN 206-101] Register 'shift_reg_1_58' is power-on initialization." projectName="up_conv" solutionName="solution1" date="2020-12-22T13:01:24.737+0300" type="Warning"/>
        <logs message="WARNING: [RTGEN 206-101] Register 'shift_reg_1_59' is power-on initialization." projectName="up_conv" solutionName="solution1" date="2020-12-22T13:01:24.716+0300" type="Warning"/>
        <logs message="WARNING: [RTGEN 206-101] Register 'shift_reg_1_60' is power-on initialization." projectName="up_conv" solutionName="solution1" date="2020-12-22T13:01:24.698+0300" type="Warning"/>
        <logs message="WARNING: [RTGEN 206-101] Register 'shift_reg_1_61' is power-on initialization." projectName="up_conv" solutionName="solution1" date="2020-12-22T13:01:24.680+0300" type="Warning"/>
        <logs message="WARNING: [RTGEN 206-101] Register 'shift_reg_1_62' is power-on initialization." projectName="up_conv" solutionName="solution1" date="2020-12-22T13:01:24.662+0300" type="Warning"/>
        <logs message="WARNING: [SYN 201-103] Legalizing function name 'Block__proc14' to 'Block_proc14'." projectName="up_conv" solutionName="solution1" date="2020-12-22T13:01:21.475+0300" type="Warning"/>
      </synLog>
      <simLog/>
      <mgLog/>
      <packageLog/>
      <csimLog/>
    </logs>
  </warningLogs>
</vivadoHLSLog:LogRoot>
